certbot_dns_solidserver/__init__.py
certbot_dns_solidserver/dns_solidserver.py
certbot_dns_solidserver-0.1.2.dist-info/LICENSE.txt
certbot_dns_solidserver-0.1.2.dist-info/METADATA
certbot_dns_solidserver-0.1.2.dist-info/WHEEL
certbot_dns_solidserver-0.1.2.dist-info/entry_points.txt
certbot_dns_solidserver-0.1.2.dist-info/top_level.txt
certbot_dns_solidserver-0.1.2.dist-info/RECORD
