Metadata-Version: 2.1
Name: certbot-dns-solidserver
Version: 0.1.2
Summary: SOLIDserver DNS Authenticator plugin for Certbot
Home-page: https://gitlab.com/charlyhong/certbot-dns-solidserver
Author: Charles Hong
Author-email: ch@efficientip.com
License: Apache License 2.0
Classifier: Development Status :: 4 - Beta
Classifier: Environment :: Plugins
Classifier: Intended Audience :: System Administrators
Classifier: License :: OSI Approved :: Apache Software License
Classifier: Operating System :: POSIX :: Linux
Classifier: Programming Language :: Python
Classifier: Programming Language :: Python :: 3
Classifier: Programming Language :: Python :: 3.6
Classifier: Programming Language :: Python :: 3.7
Classifier: Programming Language :: Python :: 3.8
Classifier: Programming Language :: Python :: 3.9
Classifier: Topic :: Internet :: WWW/HTTP
Classifier: Topic :: Security
Classifier: Topic :: System :: Installation/Setup
Classifier: Topic :: System :: Networking
Classifier: Topic :: System :: Systems Administration
Classifier: Topic :: Utilities
Requires-Python: >=3.6
License-File: LICENSE.txt
Requires-Dist: acme (>=0.29.0)
Requires-Dist: certbot (>=0.34.0)
Requires-Dist: eiprest
Requires-Dist: setuptools
